Metadata-Version: 2.1
Name: odoo12-addon-delivery-cttexpress
Version: 12.0.1.1.0
Summary: Delivery Carrier implementation for CTT Express API
Home-page: https://github.com/OCA/delivery-carrier
Author: Tecnativa, Odoo Community Association (OCA)
Author-email: support@odoo-community.org
License: AGPL-3
Platform: UNKNOWN
Classifier: Programming Language :: Python
Classifier: Framework :: Odoo
Classifier: Framework :: Odoo :: 12.0
Classifier: License :: OSI Approved :: GNU Affero General Public License v3
Requires-Python: >=3.5
Requires-Dist: odoo12-addon-delivery-package-number
Requires-Dist: odoo12-addon-delivery-state
Requires-Dist: odoo <12.1dev,>=12.0a
Requires-Dist: zeep
